setup.cfg
setup.py
yelp_kafka/__init__.py
yelp_kafka/config.py
yelp_kafka/consumer.py
yelp_kafka/consumer_group.py
yelp_kafka/discovery.py
yelp_kafka/error.py
yelp_kafka/metrics.py
yelp_kafka/metrics_responder.py
yelp_kafka/monitoring.py
yelp_kafka/offsets.py
yelp_kafka/partitioner.py
yelp_kafka/producer.py
yelp_kafka/utils.py
yelp_kafka/yelp_metrics_responder.py
yelp_kafka.egg-info/PKG-INFO
yelp_kafka.egg-info/SOURCES.txt
yelp_kafka.egg-info/dependency_links.txt
yelp_kafka.egg-info/requires.txt
yelp_kafka.egg-info/top_level.txt
yelp_kafka/testing/__init__.py
yelp_kafka/testing/kafka_mock.py