Metadata-Version: 1.1
Name: yelp-kafka
Version: 5.2.1
Summary: A library to interact with Apache Kafka at Yelp
Home-page: http://servicedocs.yelpcorp.com/docs/yelp_kafka/index.html
Author: Tools-Infra Team
Author-email: tools-infra@yelp.com
License: Copyright Yelp 2014, All Rights Reserved
Platform: UNKNOWN
Classifier: Programming Language :: Python
Classifier: Programming Language :: Python :: 2.7
Classifier: Programming Language :: Python :: 3.5
Classifier: Intended Audience :: Developers
